CustomShellCreator/__init__.py
CustomShellCreator/shell.py
CustomShellCreator-0.0.5.dist-info/LICENSE
CustomShellCreator-0.0.5.dist-info/METADATA
CustomShellCreator-0.0.5.dist-info/WHEEL
CustomShellCreator-0.0.5.dist-info/top_level.txt
CustomShellCreator-0.0.5.dist-info/RECORD
