Metadata-Version: 2.1
Name: CustomShellCreator
Version: 0.0.5
Summary: A package to create custom shells
Home-page: https://github.com/chinmaym505/CustomShellCreator
Author: Chinmay Malvania
Author-email: chinmay.malvania@gmail.com
Project-URL: Bug Tracker, https://github.com/chinmaym505/CustomShellCreator/issues
Classifier: Programming Language :: Python :: 3
Classifier: License :: OSI Approved :: Apache Software License
Classifier: Operating System :: OS Independent
Requires-Python: >=3
License-File: LICENSE
